eureka_requests/__init__.py
eureka_requests-0.0.5.dist-info/METADATA
eureka_requests-0.0.5.dist-info/WHEEL
eureka_requests-0.0.5.dist-info/top_level.txt
eureka_requests-0.0.5.dist-info/RECORD
