Metadata-Version: 2.1
Name: eureka-requests
Version: 0.0.5
Home-page: https://github.com/VK/eureka-requests
License: MIT
Keywords: Use eureka to make a request at different locations
Requires-Dist: requests
Requires-Dist: py-eureka-client
Requires-Dist: nest-asyncio
